LICENSE
MANIFEST.in
README.rst
setup.py
autoscrape/__init__.py
autoscrape/classification.py
autoscrape/control.py
autoscrape/filetypes.py
autoscrape/input_parser.py
autoscrape/tasks.py
autoscrape.egg-info/PKG-INFO
autoscrape.egg-info/SOURCES.txt
autoscrape.egg-info/dependency_links.txt
autoscrape.egg-info/entry_points.txt
autoscrape.egg-info/requires.txt
autoscrape.egg-info/top_level.txt
autoscrape/backends/__init__.py
autoscrape/backends/base/__init__.py
autoscrape/backends/base/browser.py
autoscrape/backends/base/dom.py
autoscrape/backends/base/graph.py
autoscrape/backends/base/tags.py
autoscrape/backends/requests/__init__.py
autoscrape/backends/requests/browser.py
autoscrape/backends/requests/dom.py
autoscrape/backends/requests/tags.py
autoscrape/backends/selenium/__init__.py
autoscrape/backends/selenium/browser.py
autoscrape/backends/selenium/dom.py
autoscrape/backends/selenium/tags.py
autoscrape/backends/warc/__init__.py
autoscrape/backends/warc/browser.py
autoscrape/backends/warc/dom.py
autoscrape/backends/warc/tags.py
autoscrape/cli/__init__.py
autoscrape/cli/scrape.py
autoscrape/scrapers/__init__.py
autoscrape/scrapers/manual.py
autoscrape/scrapers/null.py
autoscrape/scrapers/test.py
autoscrape/search/__init__.py
autoscrape/search/bfs.py
autoscrape/search/graph.py
autoscrape/util/__init__.py
autoscrape/util/warc.py
autoscrape/vectorization/__init__.py
autoscrape/vectorization/embeddings.py
autoscrape/vectorization/text.py
tests/tags.py
tests/test_extractor.py
tests/test_input_parser.py
tests/test_tag_generation.py