Metadata-Version: 2.1
Name: autoscrape
Version: 1.6.13
Summary: An automated, programming-free web scraper for interactive sites
Home-page: https://github.com/brandonrobertz/autoscrape-py
Author: Brandon Roberts
Author-email: brandon@bxroberts.org
License: AGPLv3
Platform: UNKNOWN
Classifier: Development Status :: 3 - Alpha
Classifier: Environment :: Console
Classifier: Intended Audience :: Developers
Classifier: Intended Audience :: End Users/Desktop
Classifier: Intended Audience :: Science/Research
Classifier: License :: OSI Approved :: GNU Affero General Public License v3
Classifier: Natural Language :: English
Classifier: Operating System :: OS Independent
Classifier: Programming Language :: Python
Classifier: Programming Language :: Python :: 3.5
Classifier: Programming Language :: Python :: 3.6
Classifier: Programming Language :: Python :: 3.7
Classifier: Programming Language :: Python :: 3.8
Classifier: Programming Language :: Python :: Implementation :: CPython
Classifier: Programming Language :: Python :: Implementation :: PyPy
Classifier: Topic :: Scientific/Engineering :: Information Analysis
Classifier: Topic :: Software Development :: Libraries :: Python Modules
Classifier: Topic :: Utilities
Provides-Extra: warc-backend
Provides-Extra: graph
Provides-Extra: all
Provides-Extra: selenium-backend
Provides-Extra: embeddings-vectorizer
